pytest_md/__init__.py
pytest_md/plugin.py
pytest_md-0.2.0.dist-info/LICENSE
pytest_md-0.2.0.dist-info/METADATA
pytest_md-0.2.0.dist-info/WHEEL
pytest_md-0.2.0.dist-info/entry_points.txt
pytest_md-0.2.0.dist-info/top_level.txt
pytest_md-0.2.0.dist-info/RECORD
